{"mode":"plan","rows":[{"no":1,"rekanan_kode":"AGM","shipment_no":"LBE2401","eta_lbe":"2024-03-31 07:00:00","volume_plan_mt":55800,"nominated_vessel":"MV Lumoso Lestari","mmsi":525013037,"loading_port":"Taboneo","eta_loading_port":null,"volume_actual_mt":55800},{"no":2,"rekanan_kode":"AGM","shipment_no":"LBE2403","eta_lbe":"2024-04-18 07:00:00","volume_plan_mt":55750,"nominated_vessel":"MV Lumoso Karunia IX","mmsi":525013037,"loading_port":"Taboneo","eta_loading_port":null,"volume_actual_mt":55750},{"no":3,"rekanan_kode":"KJA","shipment_no":"LBE2402","eta_lbe":"2024-04-20 07:00:00","volume_plan_mt":56002,"nominated_vessel":"MV Pancaran Liberty","mmsi":525013037,"loading_port":"Adang Bay","eta_loading_port":null,"volume_actual_mt":56002},{"no":4,"rekanan_kode":"KJA","shipment_no":"LBE2404","eta_lbe":"2024-04-27 07:00:00","volume_plan_mt":55003,"nominated_vessel":"MV Indrawati","mmsi":525013037,"loading_port":"Adang Bay","eta_loading_port":null,"volume_actual_mt":55003},{"no":5,"rekanan_kode":"AGM","shipment_no":"LBE2405","eta_lbe":"2024-05-02 07:00:00","volume_plan_mt":53665,"nominated_vessel":"MV Lumoso Harmoni","mmsi":525013037,"loading_port":"Taboneo","eta_loading_port":null,"volume_actual_mt":53665},{"no":6,"rekanan_kode":"AGM","shipment_no":"LBE2407","eta_lbe":"2024-05-09 07:00:00","volume_plan_mt":55570,"nominated_vessel":"MV Lumoso Lancar","mmsi":525013037,"loading_port":"Taboneo","eta_loading_port":null,"volume_actual_mt":55570},{"no":7,"rekanan_kode":"KJA","shipment_no":"LBE2406","eta_lbe":"2024-05-11 07:00:00","volume_plan_mt":56003,"nominated_vessel":"MV Pancaran Liberty","mmsi":525013037,"loading_port":"Adang Bay","eta_loading_port":null,"volume_actual_mt":56003},{"no":8,"rekanan_kode":"AGM","shipment_no":"LBE2409","eta_lbe":"2024-05-23 07:00:00","volume_plan_mt":53250,"nominated_vessel":"MV Lumoso Aman","mmsi":525013037,"loading_port":"Taboneo","eta_loading_port":null,"volume_actual_mt":53250},{"no":9,"rekanan_kode":"KJA","shipment_no":"LBE2408","eta_lbe":"2024-06-03 07:00:00","volume_plan_mt":56002,"nominated_vessel":"MV Pancaran Liberty","mmsi":525013037,"loading_port":"Adang Bay","eta_loading_port":null,"volume_actual_mt":56002},{"no":10,"rekanan_kode":"AGM","shipment_no":"LBE2411","eta_lbe":"2024-06-10 07:00:00","volume_plan_mt":46800,"nominated_vessel":"MV Lumoso Surya","mmsi":525013037,"loading_port":"Taboneo","eta_loading_port":null,"volume_actual_mt":46800},{"no":11,"rekanan_kode":"KJA","shipment_no":"LBE2410","eta_lbe":"2024-06-12 07:00:00","volume_plan_mt":48501,"nominated_vessel":"MV Manalagi Enzi","mmsi":525013037,"loading_port":"Adang Bay","eta_loading_port":null,"volume_actual_mt":48501},{"no":12,"rekanan_kode":"AGM","shipment_no":"LBE2413","eta_lbe":"2024-07-14 07:00:00","volume_plan_mt":53730,"nominated_vessel":"MV Lunioso Hawari","mmsi":525013037,"loading_port":"Taboneo","eta_loading_port":null,"volume_actual_mt":53730},{"no":13,"rekanan_kode":"AGM","shipment_no":"LBE2415","eta_lbe":"2024-07-23 07:00:00","volume_plan_mt":53300,"nominated_vessel":"MV Lumoso Aman","mmsi":525013037,"loading_port":"Taboneo","eta_loading_port":null,"volume_actual_mt":53300},{"no":14,"rekanan_kode":"KJA","shipment_no":"LBE2412","eta_lbe":"2024-08-03 07:00:00","volume_plan_mt":52007,"nominated_vessel":"MV Pancaran I 5505","mmsi":525013037,"loading_port":"Adang Bay","eta_loading_port":null,"volume_actual_mt":52007},{"no":15,"rekanan_kode":"AGM","shipment_no":"LBE2417","eta_lbe":"2024-08-07 07:00:00","volume_plan_mt":56150,"nominated_vessel":"MV Lumoso Prosper","mmsi":525013037,"loading_port":"Taboneo","eta_loading_port":null,"volume_actual_mt":56150},{"no":16,"rekanan_kode":"KJA","shipment_no":"LBE2414","eta_lbe":"2024-08-10 07:00:00","volume_plan_mt":56003,"nominated_vessel":"MV Pancaran Liberty","mmsi":525013037,"loading_port":"Adang Bay","eta_loading_port":null,"volume_actual_mt":56003},{"no":17,"rekanan_kode":"KJA","shipment_no":"LBE2416","eta_lbe":"2024-08-17 07:00:00","volume_plan_mt":51602,"nominated_vessel":"MV Manalagi Hita","mmsi":525013037,"loading_port":"Adang Bay","eta_loading_port":null,"volume_actual_mt":51602},{"no":18,"rekanan_kode":"AGM","shipment_no":"LBE2419","eta_lbe":"2024-08-23 07:00:00","volume_plan_mt":53550,"nominated_vessel":"MV Lumoso Jaya","mmsi":525013037,"loading_port":"Taboneo","eta_loading_port":null,"volume_actual_mt":53550},{"no":19,"rekanan_kode":"AGM","shipment_no":"LBE2421","eta_lbe":"2024-09-07 07:00:00","volume_plan_mt":53300,"nominated_vessel":"MV Lumoso Aman","mmsi":525013037,"loading_port":"Taboneo","eta_loading_port":null,"volume_actual_mt":53300},{"no":20,"rekanan_kode":"KJA","shipment_no":"LBE2418","eta_lbe":"2024-09-15 07:00:00","volume_plan_mt":55004,"nominated_vessel":"MV Munif","mmsi":525013037,"loading_port":"Adang Bay","eta_loading_port":null,"volume_actual_mt":55004},{"no":21,"rekanan_kode":"AGM","shipment_no":"LBE2423","eta_lbe":"2024-09-15 07:00:00","volume_plan_mt":53250,"nominated_vessel":"MV Lumoso Jaya","mmsi":525013037,"loading_port":"Taboneo","eta_loading_port":null,"volume_actual_mt":53250},{"no":22,"rekanan_kode":"KJA","shipment_no":"LBE2420","eta_lbe":"2024-09-30 07:00:00","volume_plan_mt":56007,"nominated_vessel":"MV Pancaran Liberty","mmsi":525013037,"loading_port":"Adang Bay","eta_loading_port":null,"volume_actual_mt":56007},{"no":23,"rekanan_kode":"KJA","shipment_no":"LBE2422","eta_lbe":"2024-10-05 07:00:00","volume_plan_mt":51702,"nominated_vessel":"MV Manalagi Tisya","mmsi":525013037,"loading_port":"Adang Bay","eta_loading_port":null,"volume_actual_mt":51702},{"no":24,"rekanan_kode":"AGM","shipment_no":"LBE2425","eta_lbe":"2024-10-07 07:00:00","volume_plan_mt":53400,"nominated_vessel":"MV Lumoso Jaya","mmsi":525013037,"loading_port":"Taboneo","eta_loading_port":null,"volume_actual_mt":53400},{"no":25,"rekanan_kode":"KJA","shipment_no":"LBE2424","eta_lbe":"2024-10-18 07:00:00","volume_plan_mt":57003,"nominated_vessel":"MV Mubasyir","mmsi":525013037,"loading_port":"Adang Bay","eta_loading_port":null,"volume_actual_mt":57003},{"no":26,"rekanan_kode":"AGM","shipment_no":"LBE2427","eta_lbe":"2024-10-19 07:00:00","volume_plan_mt":53200,"nominated_vessel":"MV Lumoso Aman","mmsi":525013037,"loading_port":"Taboneo","eta_loading_port":null,"volume_actual_mt":53200},{"no":27,"rekanan_kode":"KJA","shipment_no":"LBE2426","eta_lbe":"2024-10-29 07:00:00","volume_plan_mt":50253,"nominated_vessel":"MV Manalagi Samba","mmsi":525013037,"loading_port":"Adang Bay","eta_loading_port":null,"volume_actual_mt":50253},{"no":28,"rekanan_kode":"AGM","shipment_no":"LBE2429","eta_lbe":"2024-11-09 07:00:00","volume_plan_mt":53300,"nominated_vessel":"MV Lumoso Aman","mmsi":525013037,"loading_port":"Taboneo","eta_loading_port":null,"volume_actual_mt":53300},{"no":29,"rekanan_kode":"KJA","shipment_no":"LBE2428","eta_lbe":"2024-11-10 07:00:00","volume_plan_mt":48303,"nominated_vessel":"MV Manalagi Enzi","mmsi":525013037,"loading_port":"Adang Bay","eta_loading_port":null,"volume_actual_mt":48303},{"no":30,"rekanan_kode":"KJA","shipment_no":"LBE2430","eta_lbe":"2024-11-25 07:00:00","volume_plan_mt":58318,"nominated_vessel":"MV Noah Gracia","mmsi":525013037,"loading_port":"Adang Bay","eta_loading_port":null,"volume_actual_mt":58318},{"no":31,"rekanan_kode":"MIP","shipment_no":"LBE24101","eta_lbe":"2024-11-26 07:00:00","volume_plan_mt":7504,"nominated_vessel":"TB Gonaya II \/ BG MJL 3010","mmsi":525013037,"loading_port":"Sumsel","eta_loading_port":null,"volume_actual_mt":7504},{"no":32,"rekanan_kode":"MIP","shipment_no":"LBE24102","eta_lbe":"2024-12-04 07:00:00","volume_plan_mt":7380,"nominated_vessel":"TB Laurel\/BG Fitria 3009","mmsi":525013037,"loading_port":"Sumsel","eta_loading_port":null,"volume_actual_mt":7380},{"no":33,"rekanan_kode":"AGM","shipment_no":"LBE2431","eta_lbe":"2024-12-07 07:00:00","volume_plan_mt":53400,"nominated_vessel":"MV Lumoso Jaya","mmsi":525013037,"loading_port":"Taboneo","eta_loading_port":null,"volume_actual_mt":53400},{"no":34,"rekanan_kode":"AGM","shipment_no":"LBE2433","eta_lbe":"2024-12-14 07:00:00","volume_plan_mt":55850,"nominated_vessel":"MV Lumoso Karunia VIII","mmsi":525013037,"loading_port":"Taboneo","eta_loading_port":null,"volume_actual_mt":55850},{"no":35,"rekanan_kode":"MIP","shipment_no":"LBE24103","eta_lbe":"2024-12-15 07:00:00","volume_plan_mt":7567,"nominated_vessel":"TB Speedwell\/BG Gurita 3003","mmsi":525013037,"loading_port":"Sumsel","eta_loading_port":null,"volume_actual_mt":7567},{"no":36,"rekanan_kode":"MIP","shipment_no":"LBE24104","eta_lbe":"2024-12-17 07:00:00","volume_plan_mt":7561,"nominated_vessel":"TB Sorrel\/BG Gurita 3013","mmsi":525013037,"loading_port":"Sumsel","eta_loading_port":null,"volume_actual_mt":7561},{"no":37,"rekanan_kode":"AGM","shipment_no":"LBE2435","eta_lbe":"2024-12-16 07:00:00","volume_plan_mt":55700,"nominated_vessel":"MV LGH Prosper","mmsi":525013037,"loading_port":"Taboneo","eta_loading_port":null,"volume_actual_mt":55700},{"no":38,"rekanan_kode":"KJA","shipment_no":"LBE2432","eta_lbe":"2024-12-16 07:00:00","volume_plan_mt":52007,"nominated_vessel":"MV. Manalagi Tara","mmsi":525013037,"loading_port":"Adang Bay","eta_loading_port":null,"volume_actual_mt":52007},{"no":39,"rekanan_kode":"MIP","shipment_no":"LBE24105","eta_lbe":"2024-12-31 07:00:00","volume_plan_mt":7500,"nominated_vessel":"TB Sorrel\/BG Gurita 3013","mmsi":525013037,"loading_port":"Sumsel","eta_loading_port":null,"volume_actual_mt":7500},{"no":40,"rekanan_kode":"KPC","shipment_no":"LBE25104","eta_lbe":"2025-01-05 07:00:00","volume_plan_mt":60000,"nominated_vessel":"MV Maria Naswah","mmsi":525013037,"loading_port":"Sumsel","eta_loading_port":null,"volume_actual_mt":60000},{"no":41,"rekanan_kode":"NCM","shipment_no":"LBE25102","eta_lbe":"2025-01-13 07:00:00","volume_plan_mt":7234,"nominated_vessel":"TB Daya Guna\/BG Indotama Rizkindo","mmsi":525013037,"loading_port":"Sumsel","eta_loading_port":null,"volume_actual_mt":7234},{"no":42,"rekanan_kode":"NEN","shipment_no":"LBE25103","eta_lbe":"2025-01-14 07:00:00","volume_plan_mt":6818,"nominated_vessel":"TB Sabang 69\/BG Sumber Jaya","mmsi":525013037,"loading_port":"KalTim","eta_loading_port":null,"volume_actual_mt":6818},{"no":43,"rekanan_kode":"AGM","shipment_no":"LBE25105","eta_lbe":"2025-01-15 07:00:00","volume_plan_mt":53400,"nominated_vessel":"MV Lumoso Jaya","mmsi":525013037,"loading_port":"Taboneo","eta_loading_port":null,"volume_actual_mt":53400},{"no":44,"rekanan_kode":"KJA","shipment_no":"LBE2434","eta_lbe":"2025-01-24 07:00:00","volume_plan_mt":56396,"nominated_vessel":"MV. Manalagi Vira","mmsi":525013037,"loading_port":"Adang Bay","eta_loading_port":null,"volume_actual_mt":56396},{"no":45,"rekanan_kode":"AGM","shipment_no":"LBE2437","eta_lbe":"2025-01-25 07:00:00","volume_plan_mt":53600,"nominated_vessel":"MV Lumoso Hawari","mmsi":525013037,"loading_port":"Sumsel","eta_loading_port":null,"volume_actual_mt":53600},{"no":46,"rekanan_kode":"AGM","shipment_no":"LBE25106","eta_lbe":"2025-02-04 07:00:00","volume_plan_mt":55800,"nominated_vessel":"MV Lumoso Karunia IX","mmsi":525013037,"loading_port":"Taboneo","eta_loading_port":null,"volume_actual_mt":55800},{"no":47,"rekanan_kode":"KJA","shipment_no":"LBE2436","eta_lbe":"2025-02-09 07:00:00","volume_plan_mt":58002,"nominated_vessel":"MV. Noah Gracia","mmsi":525013037,"loading_port":"Adang Bay","eta_loading_port":null,"volume_actual_mt":58002},{"no":48,"rekanan_kode":"KJA","shipment_no":"LBE2438","eta_lbe":"2025-02-12 07:00:00","volume_plan_mt":56678,"nominated_vessel":"MV. Manalagi Vira","mmsi":525013037,"loading_port":"Adang Bay","eta_loading_port":null,"volume_actual_mt":56678},{"no":49,"rekanan_kode":"AGM","shipment_no":"LBE2439","eta_lbe":"2025-02-20 07:00:00","volume_plan_mt":45437,"nominated_vessel":"MV Lumoso Permai","mmsi":525013037,"loading_port":"Sumsel","eta_loading_port":null,"volume_actual_mt":45437},{"no":50,"rekanan_kode":"KJA","shipment_no":"LBE2440","eta_lbe":"2025-02-28 07:00:00","volume_plan_mt":58002,"nominated_vessel":"MV. Noah Gracia","mmsi":525013037,"loading_port":"Sumsel","eta_loading_port":null,"volume_actual_mt":58002},{"no":51,"rekanan_kode":"AGM","shipment_no":"LBE2441","eta_lbe":"2025-02-04 07:00:00","volume_plan_mt":55800,"nominated_vessel":"MV Lumoso Prosper","mmsi":525013037,"loading_port":"Taboneo","eta_loading_port":null,"volume_actual_mt":55800},{"no":52,"rekanan_kode":"KJA","shipment_no":"LBE2442","eta_lbe":"2025-03-21 07:00:00","volume_plan_mt":58002,"nominated_vessel":"MV.Manalagi Hta","mmsi":525013037,"loading_port":"Adang Bay","eta_loading_port":null,"volume_actual_mt":58002}],"report":{"rows":[{"errors":[],"warnings":[]},{"errors":[],"warnings":[]},{"errors":[],"warnings":[]},{"errors":[],"warnings":[]},{"errors":[],"warnings":[]},{"errors":[],"warnings":[]},{"errors":[],"warnings":[]},{"errors":[],"warnings":[]},{"errors":[],"warnings":[]},{"errors":[],"warnings":[]},{"errors":[],"warnings":[]},{"errors":[],"warnings":[]},{"errors":[],"warnings":[]},{"errors":[],"warnings":[]},{"errors":[],"warnings":[]},{"errors":[],"warnings":[]},{"errors":[],"warnings":[]},{"errors":[],"warnings":[]},{"errors":[],"warnings":[]},{"errors":[],"warnings":[]},{"errors":[],"warnings":[]},{"errors":[],"warnings":[]},{"errors":[],"warnings":[]},{"errors":[],"warnings":[]},{"errors":[],"warnings":[]},{"errors":[],"warnings":[]},{"errors":[],"warnings":[]},{"errors":[],"warnings":[]},{"errors":[],"warnings":[]},{"errors":[],"warnings":[]},{"errors":[],"warnings":[]},{"errors":[],"warnings":[]},{"errors":[],"warnings":[]},{"errors":[],"warnings":[]},{"errors":[],"warnings":[]},{"errors":[],"warnings":[]},{"errors":[],"warnings":[]},{"errors":[],"warnings":[]},{"errors":[],"warnings":[]},{"errors":["Shipper Code tidak terdaftar"],"warnings":[]},{"errors":[],"warnings":[]},{"errors":[],"warnings":[]},{"errors":[],"warnings":[]},{"errors":[],"warnings":[]},{"errors":[],"warnings":[]},{"errors":[],"warnings":[]},{"errors":[],"warnings":[]},{"errors":[],"warnings":[]},{"errors":[],"warnings":[]},{"errors":[],"warnings":[]},{"errors":[],"warnings":[]},{"errors":[],"warnings":[]}],"summary":{"errors":1,"warnings":0,"valid":51,"total":52}},"time":"2025-12-05T22:30:31+07:00","user":1}